setup.cfg
setup.py
sort_Sliyaniem/Merge_Sort.py
sort_Sliyaniem/__init__.py
sort_Sliyaniem.egg-info/PKG-INFO
sort_Sliyaniem.egg-info/SOURCES.txt
sort_Sliyaniem.egg-info/dependency_links.txt
sort_Sliyaniem.egg-info/not-zip-safe
sort_Sliyaniem.egg-info/top_level.txt