Metadata-Version: 1.0
Name: sort-Sliyaniem
Version: 0.1
Summary: Merge sort
Home-page: UNKNOWN
Author: UNKNOWN
Author-email: aziz89131983189@gmail.com
License: UNKNOWN
Platform: UNKNOWN
